Lab93Cryptogram/__init__.py
Lab93Cryptogram-0.0.1.dist-info/METADATA
Lab93Cryptogram-0.0.1.dist-info/WHEEL
Lab93Cryptogram-0.0.1.dist-info/top_level.txt
Lab93Cryptogram-0.0.1.dist-info/RECORD
